fishweb/__init__.py
fishweb/__main__.py
fishweb/logging.py
fishweb/app/__init__.py
fishweb/app/config.py
fishweb/app/middleware.py
fishweb/app/wrapper.py
fishweb/cmd/__init__.py
fishweb/cmd/logs.py
fishweb/cmd/main.py
fishweb/cmd/serve.py
fishweb-0.2.3.dist-info/licenses/LICENSE
fishweb-0.2.3.dist-info/METADATA
fishweb-0.2.3.dist-info/WHEEL
fishweb-0.2.3.dist-info/entry_points.txt
fishweb-0.2.3.dist-info/top_level.txt
fishweb-0.2.3.dist-info/RECORD
