Metadata-Version: 2.4
Name: fishweb
Version: 0.2.3
Summary: Your personal web app manager
Author-email: SlumberDemon <hi@sofa.sh>
Maintainer-email: lemonyte <hello@lemonyte.com>
Project-URL: Bug Reports, https://github.com/slumberdemon/fishweb/issues
Project-URL: Source, https://github.com/slumberdemon/fishweb
Project-URL: Documentation, https://fishweb.sofa.sh
Classifier: Programming Language :: Python
Requires-Python: >=3.9
License-File: LICENSE
Requires-Dist: platformdirs~=4.3.6
Requires-Dist: starlette~=0.45.3
Requires-Dist: loguru~=0.7.3
Requires-Dist: typer~=0.15.1
Requires-Dist: pydantic-settings[yaml]~=2.7.1
Provides-Extra: serve
Requires-Dist: uvicorn~=0.34.0; extra == "serve"
Provides-Extra: reload
Requires-Dist: watchdog~=2.1.5; extra == "reload"
Provides-Extra: wsgi
Requires-Dist: asgiref~=3.8.1; extra == "wsgi"
Dynamic: license-file
